jax_transformer/__init__.py
jax_transformer/embed_layer.py
jax_transformer/lora.py
jax_transformer/main.py
jax_transformer/output_head.py
jax_transformer/proj.py
jax_transformer-0.0.2.dist-info/LICENSE
jax_transformer-0.0.2.dist-info/METADATA
jax_transformer-0.0.2.dist-info/WHEEL
jax_transformer-0.0.2.dist-info/RECORD
